logical_permissions/__init__.py
logical_permissions/LogicalPermissions.py
logical_permissions/exceptions/InvalidArgumentTypeException.py
logical_permissions/exceptions/InvalidValueForLogicGateException.py
logical_permissions/exceptions/__init__.py
logical_permissions/exceptions/InvalidArgumentValueException.py
logical_permissions/exceptions/PermissionTypeAlreadyExistsException.py
logical_permissions/exceptions/InvalidCallbackReturnTypeException.py
logical_permissions/exceptions/PermissionTypeNotRegisteredException.py
logical_permissions-1.2.5.dist-info/top_level.txt
logical_permissions-1.2.5.dist-info/metadata.json
logical_permissions-1.2.5.dist-info/RECORD
logical_permissions-1.2.5.dist-info/METADATA
logical_permissions-1.2.5.dist-info/WHEEL
logical_permissions-1.2.5.dist-info/DESCRIPTION.rst
