Metadata-Version: 2.0
Name: logical-permissions
Version: 1.2.5
Summary: Provides support for dictionary-based permissions with logic gates such as AND and OR.
Home-page: https://github.com/ordermind/logical-permissions-py
Author: Kristofer Tengström
Author-email: ordermind@gmail.com
License: MIT
Keywords: permissions
Platform: UNKNOWN
Classifier: Development Status :: 5 - Production/Stable
Classifier: Intended Audience :: Developers
Classifier: Topic :: Software Development :: Libraries :: Python Modules
Classifier: Programming Language :: Python :: 2
Classifier: Programming Language :: Python :: 2.7
Classifier: Programming Language :: Python :: 3
Classifier: Programming Language :: Python :: 3.2
Classifier: Programming Language :: Python :: 3.3
Classifier: Programming Language :: Python :: 3.4
Classifier: Programming Language :: Python :: 3.5
Classifier: Programming Language :: Python :: 3.6
